plutonium/__init__.py
plutonium/bounty.py
plutonium/player.py
plutonium/practice.py
plutonium/server.py
plutonium/top.py
Plutonium_MCPE-0.0.1.dist-info/LICENSE
Plutonium_MCPE-0.0.1.dist-info/METADATA
Plutonium_MCPE-0.0.1.dist-info/WHEEL
Plutonium_MCPE-0.0.1.dist-info/top_level.txt
Plutonium_MCPE-0.0.1.dist-info/RECORD
